mcp_think/__about__.py
mcp_think/__init__.py
mcp_think/__main__.py
mcp_think/server.py
mcp_think-0.2.2.dist-info/licenses/LICENSE
mcp_think-0.2.2.dist-info/METADATA
mcp_think-0.2.2.dist-info/WHEEL
mcp_think-0.2.2.dist-info/entry_points.txt
mcp_think-0.2.2.dist-info/top_level.txt
mcp_think-0.2.2.dist-info/RECORD
