Metadata-Version: 2.4
Name: mcp-think
Version: 0.2.2
Summary: An MCP server implementing the think tool for Claude and other LLMs
Home-page: https://github.com/ddkang1/mcp-think
Author: Don Kang
Author-email: Don Kang <donkang34@gmail.com>
License: MIT License
Project-URL: Homepage, https://github.com/ddkang1/mcp-think
Project-URL: Bug Tracker, https://github.com/ddkang1/mcp-think/issues
Project-URL: Documentation, https://github.com/ddkang1/mcp-think#readme
Classifier: Development Status :: 3 - Alpha
Classifier: Intended Audience :: Developers
Classifier: License :: OSI Approved :: MIT License
Classifier: Programming Language :: Python :: 3
Classifier: Programming Language :: Python :: 3.10
Requires-Python: >=3.10
License-File: LICENSE
Requires-Dist: mcp>=1.2.0
Requires-Dist: uvicorn>=0.15.0
Requires-Dist: starlette>=0.17.1
Provides-Extra: dev
Requires-Dist: pytest>=7.0.0; extra == "dev"
Requires-Dist: pytest-asyncio>=0.18.0; extra == "dev"
Requires-Dist: black>=22.1.0; extra == "dev"
Requires-Dist: isort>=5.10.1; extra == "dev"
Requires-Dist: mypy>=0.931; extra == "dev"
Requires-Dist: flake8>=4.0.1; extra == "dev"
Dynamic: author
Dynamic: home-page
Dynamic: license-file
Dynamic: requires-python
